{"_ts":[1491460296,1492669668],"_r":{"breakdown":{"html":{"bytes":[16423,16499],"requests":[2,2]},"js":{"bytes":[191270,192275],"requests":[12,12]},"css":{"bytes":[44053,44285],"requests":[7,7]},"image":{"bytes":[822265,822241],"requests":[21,21]},"flash":{"bytes":[0,0],"requests":[0,0]},"font":{"bytes":[58776,59196],"requests":[4,4]},"other":{"bytes":[0,0],"requests":[0,0]}},"date":[1491460296,1492669668],"domElements":[1122,1127],"domInteractive":[2502,2704],"firstPaint":[2450,2511],"fullyLoaded":[7780,7832],"id":["170406_P0_BB2","170420_CK_CDF"],"loadTime":[7647,7694],"render":[2678,2576],"SpeedIndex":[5494,5355],"TTFB":[590,632],"videoFrames":[[{"_t":0,"_vc":0},{"_t":2700,"_vc":43},{"_t":3400,"_vc":50},{"_t":3600,"_vc":49},{"_t":3800,"_vc":49},{"_t":8100,"_vc":100}],[{"_t":0,"_vc":0},{"_t":2600,"_vc":43},{"_t":3500,"_vc":50},{"_t":3700,"_vc":49},{"_t":4200,"_vc":49},{"_t":7900,"_vc":100}]],"visualComplete":[8100,7900]}}