{"_ts":[1520317566,1520922356],"_r":{"breakdown":{"html":{"bytes":[14215,13825],"requests":[2,2]},"js":{"bytes":[79967,79712],"requests":[8,8]},"css":{"bytes":[118782,118709],"requests":[7,7]},"image":{"bytes":[650598,642406],"requests":[8,8]},"flash":{"bytes":[0,0],"requests":[0,0]},"font":{"bytes":[0,0],"requests":[0,0]},"video":{"bytes":[0,0],"requests":[0,0]},"other":{"bytes":[0,0],"requests":[0,0]}},"date":[1520317566,1520922356],"domElements":[903,903],"domInteractive":[2651,2462],"firstPaint":[2645.7999999984,2457.0999999996],"fullyLoaded":[8156,7280],"id":["180306_ER_f2b6ce44edaa9e9198455db3abc5f4a6","180313_G8_0e6bd94a2e9bda1f2e0eb93b4d9d9ee2"],"loadTime":[5111,4182],"render":[2600,2400],"SpeedIndex":[3211,3001],"TTFB":[865,636],"videoFrames":[[{"_t":0,"_vc":0},{"_t":2600,"_vc":71},{"_t":2700,"_vc":72},{"_t":2800,"_vc":72},{"_t":2900,"_vc":72},{"_t":3000,"_vc":72},{"_t":3100,"_vc":72},{"_t":3200,"_vc":72},{"_t":3300,"_vc":71},{"_t":3400,"_vc":71},{"_t":3500,"_vc":71},{"_t":3600,"_vc":71},{"_t":3700,"_vc":71},{"_t":3800,"_vc":71},{"_t":3900,"_vc":71},{"_t":4000,"_vc":71},{"_t":4100,"_vc":71},{"_t":4200,"_vc":71},{"_t":4300,"_vc":71},{"_t":4400,"_vc":71},{"_t":4500,"_vc":71},{"_t":4600,"_vc":71},{"_t":4700,"_vc":92},{"_t":4800,"_vc":100},{"_t":4900,"_vc":100},{"_t":5400,"_vc":100},{"_t":5500,"_vc":100}],[{"_t":0,"_vc":0},{"_t":2400,"_vc":71},{"_t":2500,"_vc":72},{"_t":2600,"_vc":72},{"_t":2700,"_vc":72},{"_t":2800,"_vc":72},{"_t":2900,"_vc":72},{"_t":3000,"_vc":71},{"_t":3100,"_vc":70},{"_t":3200,"_vc":70},{"_t":3300,"_vc":70},{"_t":3400,"_vc":71},{"_t":3500,"_vc":71},{"_t":3600,"_vc":71},{"_t":3700,"_vc":71},{"_t":3800,"_vc":71},{"_t":3900,"_vc":71},{"_t":4000,"_vc":71},{"_t":4100,"_vc":71},{"_t":4200,"_vc":71},{"_t":4300,"_vc":71},{"_t":4400,"_vc":79},{"_t":4500,"_vc":99},{"_t":4600,"_vc":99},{"_t":4700,"_vc":100},{"_t":5100,"_vc":100},{"_t":5200,"_vc":100}]],"visualComplete":[4800,4700]}}