{"_ts":[1530685826],"_r":{"breakdown":{"html":{"bytes":[14322],"requests":[2]},"js":{"bytes":[79489],"requests":[8]},"css":{"bytes":[115504],"requests":[7]},"image":{"bytes":[314643],"requests":[7]},"flash":{"bytes":[0],"requests":[0]},"font":{"bytes":[0],"requests":[0]},"video":{"bytes":[0],"requests":[0]},"other":{"bytes":[0],"requests":[0]}},"date":[1530685826],"domElements":[907],"domInteractive":[2269],"firstPaint":[2260.2999999999],"fullyLoaded":[4857],"id":["180704_3T_57866d7a813600e116d0e201520b6c83"],"loadTime":[4708],"render":[2300],"SpeedIndex":[2896],"TTFB":[595],"videoFrames":[[{"_t":0,"_vc":0},{"_t":2300,"_vc":71},{"_t":2400,"_vc":70},{"_t":2500,"_vc":70},{"_t":2600,"_vc":70},{"_t":2700,"_vc":70},{"_t":2800,"_vc":70},{"_t":2900,"_vc":70},{"_t":3000,"_vc":70},{"_t":3100,"_vc":70},{"_t":3200,"_vc":70},{"_t":3300,"_vc":70},{"_t":3400,"_vc":70},{"_t":3500,"_vc":70},{"_t":3600,"_vc":71},{"_t":3700,"_vc":71},{"_t":3800,"_vc":71},{"_t":3900,"_vc":71},{"_t":4000,"_vc":71},{"_t":4100,"_vc":71},{"_t":4200,"_vc":72},{"_t":4300,"_vc":95},{"_t":4400,"_vc":100}]],"visualComplete":[4400]}}